opa_wasmtime/__init__.py
opa_wasmtime/benchmark.py
opa_wasmtime/opa_wasmtime.py
opa_wasmtime-0.1.1.dist-info/licenses/LICENSE
opa_wasmtime-0.1.1.dist-info/METADATA
opa_wasmtime-0.1.1.dist-info/WHEEL
opa_wasmtime-0.1.1.dist-info/top_level.txt
opa_wasmtime-0.1.1.dist-info/RECORD
