Metadata-Version: 2.4
Name: opa-wasmtime
Version: 0.1.1
Summary: OPA WebAssembly SDK for Python based on wasmtime
License: MIT
Project-URL: Source, https://github.com/nickdeis/python-opa-wasmtime
Requires-Python: >=3.10
License-File: LICENSE
Requires-Dist: wasmtime>=27.0.2
Dynamic: license-file
